foliant/preprocessors/admonitions.py
foliantcontrib.admonitions-1.0.1.dist-info/LICENSE
foliantcontrib.admonitions-1.0.1.dist-info/METADATA
foliantcontrib.admonitions-1.0.1.dist-info/WHEEL
foliantcontrib.admonitions-1.0.1.dist-info/top_level.txt
foliantcontrib.admonitions-1.0.1.dist-info/RECORD
